blissdata/__init__.py
blissdata/deprecation.py
blissdata/exceptions.py
blissdata/py.typed
blissdata/scan.py
blissdata/beacon/__init__.py
blissdata/beacon/_base.py
blissdata/beacon/_utils.py
blissdata/beacon/config.py
blissdata/beacon/data.py
blissdata/beacon/files.py
blissdata/h5api/__init__.py
blissdata/h5api/abstract.py
blissdata/h5api/dynamic_hdf5.py
blissdata/h5api/file_arguments.py
blissdata/h5api/h5_scan_map.py
blissdata/h5api/redis_hdf5.py
blissdata/h5api/static_hdf5.py
blissdata/h5api/utils/__init__.py
blissdata/h5api/utils/bliss.py
blissdata/h5api/utils/hdf5.py
blissdata/h5api/utils/hdf5_retry.py
blissdata/h5api/utils/lima.py
blissdata/h5api/utils/types.py
blissdata/h5map/__init__.py
blissdata/h5map/data_items.py
blissdata/h5map/hdf5_items.py
blissdata/lima/__init__.py
blissdata/lima/client.py
blissdata/lima/image_utils.py
blissdata/redis_engine/__init__.py
blissdata/redis_engine/event_stream.py
blissdata/redis_engine/exceptions.py
blissdata/redis_engine/identities.py
blissdata/redis_engine/memory_tracker.py
blissdata/redis_engine/scan.py
blissdata/redis_engine/store.py
blissdata/redis_engine/encoding/__init__.py
blissdata/redis_engine/encoding/json.py
blissdata/redis_engine/encoding/numeric.py
blissdata/schemas/__init__.py
blissdata/schemas/scan_info.py
blissdata/schemas/scan_info_display.py
blissdata/streams/__init__.py
blissdata/streams/base.py
blissdata/streams/default.py
blissdata/streams/event_stream.py
blissdata/streams/sink.py
blissdata/streams/encoding/__init__.py
blissdata/streams/encoding/json.py
blissdata/streams/encoding/numeric.py
blissdata/streams/hdf5_fallback/__init__.py
blissdata/streams/hdf5_fallback/stream.py
blissdata/streams/lima/__init__.py
blissdata/streams/lima/stream.py
blissdata/streams/scan_sequence/__init__.py
blissdata/streams/scan_sequence/stream.py
blissdata/tests/__init__.py
blissdata/tests/conftest.py
blissdata/tests/beacon/__init__.py
blissdata/tests/beacon/test_config.py
blissdata/tests/beacon/test_data.py
blissdata-2.3.0.dist-info/licenses/LICENSE
blissdata-2.3.0.dist-info/METADATA
blissdata-2.3.0.dist-info/WHEEL
blissdata-2.3.0.dist-info/entry_points.txt
blissdata-2.3.0.dist-info/top_level.txt
blissdata-2.3.0.dist-info/RECORD
