Metadata-Version: 2.4
Name: blissdata
Version: 2.3.0
Summary: Bliss data streaming client
Maintainer: BCU (ESRF)
License-Expression: LGPL-3.0-or-later
Project-URL: Repository, https://gitlab.esrf.fr/bliss/blissdata/
Project-URL: Documentation, https://bliss.gitlab-pages.esrf.fr/blissdata/
Project-URL: Changes, https://gitlab.esrf.fr/bliss/blissdata/-/blob/master/CHANGELOG.md
Classifier: Intended Audience :: Science/Research
Classifier: Operating System :: OS Independent
Classifier: Programming Language :: Python :: 3
Requires-Python: >=3.10
License-File: LICENSE
Requires-Dist: beartype
Requires-Dist: fabio>=0.12
Requires-Dist: h5py>=2.9
Requires-Dist: msgpack
Requires-Dist: numpy>=1.20
Requires-Dist: numpydantic<1.6.10
Requires-Dist: pydantic>=2.3.0
Requires-Dist: redis>=4.6.0
Requires-Dist: redis-om<1.0,>=0.3.1
Requires-Dist: silx>=1.1.0
Provides-Extra: tango
Requires-Dist: pytango>=9.3.1; extra == "tango"
Provides-Extra: lima2
Requires-Dist: blissdata-lima2>=2.0; extra == "lima2"
Provides-Extra: test
Requires-Dist: gevent>=20.9.0; extra == "test"
Requires-Dist: pytest>=7; extra == "test"
Requires-Dist: pytest-mock; extra == "test"
Requires-Dist: pytest-redis>=3.1; extra == "test"
Requires-Dist: pytest-timeout; extra == "test"
Requires-Dist: packaging; extra == "test"
Provides-Extra: dev
Requires-Dist: blissdata[test]; extra == "dev"
Requires-Dist: black==22.3; extra == "dev"
Requires-Dist: flake8>=4; extra == "dev"
Requires-Dist: flake8-pep585; extra == "dev"
Requires-Dist: mkdocs; extra == "dev"
Requires-Dist: mkdocs-material; extra == "dev"
Requires-Dist: mkdocstrings[python]>=0.18; extra == "dev"
Provides-Extra: beacon
Requires-Dist: ruamel.yaml; extra == "beacon"
Dynamic: license-file
